themusharraf_utils/__init__.py
themusharraf_utils/utils.py
themusharraf_utils-0.1.2.dist-info/licenses/LICENSE
themusharraf_utils-0.1.2.dist-info/METADATA
themusharraf_utils-0.1.2.dist-info/WHEEL
themusharraf_utils-0.1.2.dist-info/top_level.txt
themusharraf_utils-0.1.2.dist-info/RECORD
