Metadata-Version: 2.4
Name: themusharraf-utils
Version: 0.1.2
Summary: A collection of useful Python utilities by Musharraf
Author-email: Musharraf Ibragimov <meibrohimov@gmail.com>
License: MIT
Project-URL: Homepage, https://github.com/themusharraf/themusharraf-utils
Project-URL: Issues, https://github.com/themusharraf/themusharraf-utils/issues
Requires-Python: >=3.8
License-File: LICENSE
Dynamic: license-file
